smartapi/__init__.py
smartapi/api_client.py
smartapi/api_client_bindings.py
smartapi/api_client_core.py
smartapi/api_client_endpoints.py
smartapi/api_client_errors.py
smartapi/api_client_openapi.py
smartapi/api_client_postman.py
smartapi/api_client_requests.py
smartapi/api_client_response.py
smartapi/cli.py
smartapi/config.py
smartapi/errors.py
smartapi/utils.py
smartapi_client-0.1.15.dist-info/LICENSE
smartapi_client-0.1.15.dist-info/METADATA
smartapi_client-0.1.15.dist-info/WHEEL
smartapi_client-0.1.15.dist-info/entry_points.txt
smartapi_client-0.1.15.dist-info/RECORD
